quikenv/__init__.py
quikenv/custom_exceptions.py
quikenv/main.py
quikenv-1.0.0.dist-info/LICENSE
quikenv-1.0.0.dist-info/METADATA
quikenv-1.0.0.dist-info/WHEEL
quikenv-1.0.0.dist-info/top_level.txt
quikenv-1.0.0.dist-info/RECORD
